robocorp/windows/__init__.py
robocorp/windows/_com_error.py
robocorp/windows/_config.py
robocorp/windows/_config_uiautomation.py
robocorp/windows/_control_element.py
robocorp/windows/_desktop.py
robocorp/windows/_errors.py
robocorp/windows/_find_ui_automation.py
robocorp/windows/_find_window.py
robocorp/windows/_func_lru_cache.py
robocorp/windows/_func_robocorp_tasks_cache.py
robocorp/windows/_icon_from_file.py
robocorp/windows/_inspect.py
robocorp/windows/_iter_tree.py
robocorp/windows/_match_ast.py
robocorp/windows/_match_common.py
robocorp/windows/_match_tokenization.py
robocorp/windows/_processes.py
robocorp/windows/_screenshot.py
robocorp/windows/_ui_automation_wrapper.py
robocorp/windows/_vendored/__init__.py
robocorp/windows/_vendored/uiautomation/__init__.py
robocorp/windows/_vendored/uiautomation/bin/UIAutomationClient_VC140_X64.dll
robocorp/windows/_vendored/uiautomation/bin/UIAutomationClient_VC140_X86.dll
robocorp/windows/_vendored/uiautomation/uiautomation.py
robocorp/windows/_vendored/uiautomation/version.py
robocorp/windows/_window_element.py
robocorp/windows/protocols.py
robocorp/windows/py.typed
robocorp_windows-1.0.4.dist-info/METADATA
robocorp_windows-1.0.4.dist-info/WHEEL
robocorp_windows-1.0.4.dist-info/RECORD
